lovematch/__init__.py
lovematch/friendship.py
lovematch/love.py
lovematch-1.8.0.dist-info/LICENSE
lovematch-1.8.0.dist-info/METADATA
lovematch-1.8.0.dist-info/WHEEL
lovematch-1.8.0.dist-info/top_level.txt
lovematch-1.8.0.dist-info/RECORD
